{
  "Dlcs": {
    "1366091": {
      "Name": "Frog Fractions GotDE - Hop's Iconic Cap",
      "AppId": 1366091,
      "ImageUrl": "https://cdn.akamai.steamstatic.com/steam/apps/1366091/header.jpg",
      "MainAppId": 1194840,
      "Type": "dlc"
    },
    "1366090": {
      "Name": "Frog Fractions GotDE - OST",
      "AppId": 1366090,
      "ImageUrl": "https://cdn.akamai.steamstatic.com/steam/apps/1366090/header.jpg",
      "MainAppId": 1194840
    }
  },
  "Name": "Frog Fractions: Game of the Decade Edition",
  "AppId": 1194840,
  "ImageUrl": "https://cdn.akamai.steamstatic.com/steam/apps/1194840/header.jpg",
  "Languages": [
    "english"
  ],
  "Type": "game"
}