[
  {
    "name": "foodForTheVoid",
    "displayName": "foodForTheVoid",
    "type": "int",
    "default": 0,
    "incrementonly": true,
    "aggregated": false,
    "maxchange": 1
  },
  {
    "name": "killsDemonBoss",
    "displayName": "killsDemonBoss",
    "type": "int",
    "default": 0,
    "incrementonly": true,
    "aggregated": false,
    "maxchange": 1
  },
  {
    "name": "killsDemonEnvy",
    "displayName": "killsDemonEnvy",
    "type": "int",
    "default": 0,
    "incrementonly": true,
    "aggregated": false,
    "maxchange": 1
  },
  {
    "name": "killsDemonGluttony",
    "displayName": "killsDemonGluttony",
    "type": "int",
    "default": 0,
    "incrementonly": true,
    "aggregated": false,
    "maxchange": 1
  },
  {
    "name": "killsDemonPride",
    "displayName": "killsDemonPride",
    "type": "int",
    "default": 0,
    "incrementonly": true,
    "aggregated": false,
    "maxchange": 1
  },
  {
    "name": "killsDemonSloth",
    "displayName": "killsDemonSloth",
    "type": "int",
    "default": 0,
    "incrementonly": true,
    "aggregated": false,
    "maxchange": 1
  },
  {
    "name": "killsDemonWrath",
    "displayName": "killsDemonWrath",
    "type": "int",
    "default": 0,
    "incrementonly": true,
    "aggregated": false,
    "maxchange": 1
  },
  {
    "name": "killsGhoulBoss",
    "displayName": "killsGhoulBoss",
    "type": "int",
    "default": 0,
    "incrementonly": true,
    "aggregated": false,
    "maxchange": 1
  },
  {
    "name": "killsGhoulFestering",
    "displayName": "killsGhoulFestering",
    "type": "int",
    "default": 0,
    "incrementonly": true,
    "aggregated": false,
    "maxchange": 1
  },
  {
    "name": "killsGhoulGrotesque",
    "displayName": "killsGhoulGrotesque",
    "type": "int",
    "default": 0,
    "incrementonly": true,
    "aggregated": false,
    "maxchange": 1
  },
  {
    "name": "killsGhoulScavenger",
    "displayName": "killsGhoulScavenger",
    "type": "int",
    "default": 0,
    "incrementonly": true,
    "aggregated": false
  },
  {
    "name": "killsGhoulShredder",
    "displayName": "killsGhoulShredder",
    "type": "int",
    "default": 0,
    "incrementonly": true,
    "aggregated": false
  },
  {
    "name": "killsMiniSkels",
    "displayName": "killsMiniSkels",
    "type": "int",
    "default": 0,
    "incrementonly": true,
    "aggregated": false,
    "maxchange": 1
  },
  {
    "name": "killsSkeletonBoss",
    "displayName": "killsSkeletonBoss",
    "type": "int",
    "default": 0,
    "incrementonly": true,
    "aggregated": false,
    "maxchange": 1
  },
  {
    "name": "killsSkeletonArcher",
    "displayName": "killsSkeletonArcher",
    "type": "int",
    "default": 0,
    "incrementonly": true,
    "aggregated": false,
    "maxchange": 1
  },
  {
    "name": "killsSkeletonBrute",
    "displayName": "killsSkeletonBrute",
    "type": "int",
    "default": 0,
    "incrementonly": true,
    "aggregated": false
  },
  {
    "name": "killsSkeletonBruteElite",
    "displayName": "killsSkeletonElite",
    "type": "int",
    "default": 0,
    "incrementonly": true,
    "aggregated": false
  },
  {
    "name": "killsSkeletonBruteTough",
    "displayName": "killsSkeletonTough",
    "type": "int",
    "default": 0,
    "incrementonly": true,
    "aggregated": false,
    "maxchange": 1
  },
  {
    "name": "killsSkeletonMage",
    "displayName": "killsSkeletonMage",
    "type": "int",
    "default": 0,
    "incrementonly": true,
    "aggregated": false,
    "maxchange": 1
  },
  {
    "name": "killsSkeletonMageElite",
    "displayName": "killsSkeletonMageElite",
    "type": "int",
    "default": 0,
    "incrementonly": true,
    "aggregated": false,
    "maxchange": 1
  },
  {
    "name": "killsSkeletonMageTough",
    "displayName": "killsSkeletonMageTough",
    "type": "int",
    "default": 0,
    "incrementonly": true,
    "aggregated": false,
    "maxchange": 1
  },
  {
    "name": "killsSkeletonKnight",
    "displayName": "killsSkeletonKnight",
    "type": "int",
    "default": 0,
    "incrementonly": true,
    "aggregated": false,
    "maxchange": 1
  },
  {
    "name": "killsSkeletonKnightElite",
    "displayName": "killsSkeletonKnightElite",
    "type": "int",
    "default": 0,
    "incrementonly": true,
    "aggregated": false,
    "maxchange": 1
  },
  {
    "name": "killsZombieBoss",
    "displayName": "killsZombieBoss",
    "type": "int",
    "default": 0,
    "incrementonly": true,
    "aggregated": false,
    "maxchange": 1
  },
  {
    "name": "killsZombieFlatulator",
    "displayName": "killsZombieFlatulator",
    "type": "int",
    "default": 0,
    "incrementonly": true,
    "aggregated": false,
    "maxchange": 1
  },
  {
    "name": "killsZombieMurderer",
    "displayName": "killsZombieMurderer",
    "type": "int",
    "default": 0,
    "incrementonly": true,
    "aggregated": false,
    "maxchange": 1
  },
  {
    "name": "killsZombiePeon",
    "displayName": "killsZombiePeon",
    "type": "int",
    "default": 0,
    "incrementonly": true,
    "aggregated": false,
    "maxchange": 1
  },
  {
    "name": "killsZombieSnapper",
    "displayName": "killsZombieSnapper",
    "type": "int",
    "default": 0,
    "incrementonly": true,
    "aggregated": false,
    "maxchange": 1
  },
  {
    "name": "pocketDimensions",
    "displayName": "pocketDimensions",
    "type": "int",
    "default": 0,
    "incrementonly": true,
    "aggregated": false,
    "maxchange": 1
  },
  {
    "name": "treasurePiles",
    "displayName": "treasurePiles",
    "type": "int",
    "default": 0,
    "incrementonly": true,
    "aggregated": false,
    "maxchange": 1
  }
]