[
  {
    "appid": "3067050",
    "itemdefid": "10",
    "Timestamp": "2024-07-24T15:15:53Z",
    "modified": "20240724T151553Z",
    "date_created": "20240705T211635Z",
    "type": "item",
    "display_type": "",
    "name": "Pug",
    "quantity": 1,
    "description": "Can't get more basic than this!\n\nRarity: Common",
    "icon_url": "https://i.ibb.co/dWpncZK/pug-color1.png",
    "tradable": true,
    "marketable": true,
    "commodity": false,
    "quality": " common"
  },
  {
    "appid": "3067050",
    "itemdefid": "11",
    "Timestamp": "2024-07-24T15:20:04Z",
    "modified": "20240724T152004Z",
    "date_created": "20240705T211637Z",
    "type": "item",
    "display_type": "",
    "name": "Caramel Pug",
    "quantity": 1,
    "description": "Caramel Color Pug, he's not a candy\n\nRarity: Common",
    "icon_url": "https://i.ibb.co/V2HZjmM/pug-color2.png",
    "tradable": true,
    "marketable": true,
    "commodity": false,
    "quality": "common"
  },
  {
    "appid": "3067050",
    "itemdefid": "12",
    "Timestamp": "2024-07-24T15:19:56Z",
    "modified": "20240724T151956Z",
    "date_created": "20240705T211637Z",
    "type": "item",
    "display_type": "",
    "name": "Chocolat Pug",
    "quantity": 1,
    "description": "Chocolat Color Pug, he's not real chocolat\n\nRarity: Common",
    "icon_url": "https://i.ibb.co/wSLdngt/pug-color3.png",
    "tradable": true,
    "marketable": true,
    "commodity": false,
    "quality": "common"
  },
  {
    "appid": "3067050",
    "itemdefid": "13",
    "Timestamp": "2024-07-24T15:23:32Z",
    "modified": "20240724T152332Z",
    "date_created": "20240705T211637Z",
    "type": "item",
    "display_type": "",
    "name": "White Pug",
    "quantity": 1,
    "description": "White Color Pug\n\nRarity: Common",
    "icon_url": "https://i.ibb.co/HFcW0nV/pug-color4.png",
    "tradable": true,
    "marketable": true,
    "commodity": false,
    "quality": "common"
  },
  {
    "appid": "3067050",
    "itemdefid": "14",
    "Timestamp": "2024-08-17T14:40:19Z",
    "modified": "20240817T144019Z",
    "date_created": "20240705T211637Z",
    "type": "item",
    "display_type": "",
    "name": "Albino Pug",
    "quantity": 1,
    "description": "He's home isn't in a Lab\n\nRarity: Uncommon\n\nNo longer Drops",
    "icon_url": "https://i.ibb.co/8NHmvgY/pug-color5.png",
    "tradable": true,
    "marketable": true,
    "commodity": false,
    "quality": "common"
  },
  {
    "appid": "3067050",
    "itemdefid": "15",
    "Timestamp": "2024-07-24T15:18:59Z",
    "modified": "20240724T151859Z",
    "date_created": "20240705T211637Z",
    "type": "item",
    "display_type": "",
    "name": "Black Pug",
    "quantity": 1,
    "description": "Black color Pug\n\nRarity: Common",
    "icon_url": "https://i.ibb.co/6PW2SmB/pug-color6.png",
    "tradable": true,
    "marketable": true,
    "commodity": false,
    "quality": "common"
  },
  {
    "appid": "3067050",
    "itemdefid": "20",
    "Timestamp": "2024-07-24T15:20:52Z",
    "modified": "20240724T152052Z",
    "date_created": "20240705T221820Z",
    "type": "item",
    "display_type": "",
    "name": "Pugermelon",
    "quantity": 1,
    "description": "Watermelons are 92% water and 8% sugar. They can grow with or without seeds, this one grew with a pug.\n\nRarity: Common",
    "icon_url": "https://i.ibb.co/T2M0Lqz/pug-fruit2.png",
    "tradable": true,
    "marketable": true,
    "commodity": false,
    "quality": "common"
  },
  {
    "appid": "3067050",
    "itemdefid": "21",
    "Timestamp": "2024-07-24T15:21:00Z",
    "modified": "20240724T152100Z",
    "date_created": "20240705T221820Z",
    "type": "item",
    "display_type": "",
    "name": "StrawPugerry",
    "quantity": 1,
    "description": "The average strawPugerry has 200 seeds and a 1/2 of a pug.\n\nRarity: Common",
    "icon_url": "https://i.ibb.co/J2rG84P/pug-fruit3.png",
    "tradable": true,
    "marketable": true,
    "commodity": false,
    "quality": "common"
  },
  {
    "appid": "3067050",
    "itemdefid": "22",
    "Timestamp": "2024-07-24T15:21:05Z",
    "modified": "20240724T152105Z",
    "date_created": "20240705T221820Z",
    "type": "item",
    "display_type": "",
    "name": "Pugnapple",
    "quantity": 1,
    "description": "I wonder if he also lives under the sea.\n\nRarity: Common",
    "icon_url": "https://i.ibb.co/cgnM8NG/pug-fruit4.png",
    "tradable": true,
    "marketable": true,
    "commodity": false,
    "quality": "common"
  },
  {
    "appid": "3067050",
    "itemdefid": "23",
    "Timestamp": "2024-07-24T15:25:44Z",
    "modified": "20240724T152544Z",
    "date_created": "20240705T221820Z",
    "type": "item",
    "display_type": "",
    "name": "Pugpaya",
    "quantity": 1,
    "description": "Pugpayas are a high source of vitamin C. One medium pugpaya has approximately: 120 calories.\n\nRarity: Common",
    "icon_url": "https://i.ibb.co/D4n2wsp/pug-fruit5.png",
    "tradable": true,
    "marketable": true,
    "commodity": false,
    "quality": "common"
  },
  {
    "appid": "3067050",
    "itemdefid": "24",
    "Timestamp": "2024-07-24T15:21:12Z",
    "modified": "20240724T152112Z",
    "date_created": "20240705T221820Z",
    "type": "item",
    "display_type": "",
    "name": "Pugoconut",
    "quantity": 1,
    "description": "A coconut tree can have up to 180 coconuts harvested during a single harvest, and only a 1% chance to get a pugoconut.\n\nRarity: Common",
    "icon_url": "https://i.ibb.co/SQ6wfcB/pug-pugonut.png",
    "tradable": true,
    "marketable": true,
    "commodity": false,
    "quality": "common"
  },
  {
    "appid": "3067050",
    "itemdefid": "30",
    "Timestamp": "2024-07-24T15:21:41Z",
    "modified": "20240724T152141Z",
    "date_created": "20240705T221820Z",
    "type": "item",
    "display_type": "",
    "name": "Iron Pug",
    "quantity": 1,
    "description": "A bit Shiny!\n\nRarity: Common",
    "icon_url": "https://i.ibb.co/6JkZdD2/pug-metal1.png",
    "tradable": true,
    "marketable": true,
    "commodity": false,
    "quality": "common"
  },
  {
    "appid": "3067050",
    "itemdefid": "31",
    "Timestamp": "2024-07-24T15:23:11Z",
    "modified": "20240724T152311Z",
    "date_created": "20240705T221820Z",
    "type": "item",
    "display_type": "",
    "name": "Bronze Pug",
    "quantity": 1,
    "description": "Shiny!\n\nRarity: Uncommon",
    "icon_url": "https://i.ibb.co/zGrTNvt/pug-metal2.png",
    "tradable": true,
    "marketable": true,
    "commodity": false,
    "quality": "common"
  },
  {
    "appid": "3067050",
    "itemdefid": "32",
    "Timestamp": "2024-07-24T15:23:44Z",
    "modified": "20240724T152344Z",
    "date_created": "20240705T221820Z",
    "type": "item",
    "display_type": "",
    "name": "Silver Pug",
    "quantity": 1,
    "description": "Very Shiny!\n\nRarity: Rare",
    "icon_url": "https://i.ibb.co/S64jZ6J/pug-metal3.png",
    "tradable": true,
    "marketable": true,
    "commodity": false,
    "quality": "common"
  },
  {
    "appid": "3067050",
    "itemdefid": "33",
    "Timestamp": "2024-07-24T15:25:24Z",
    "modified": "20240724T152524Z",
    "date_created": "20240705T221820Z",
    "type": "item",
    "display_type": "",
    "name": "Golden Pug",
    "quantity": 1,
    "description": "Extremely Shiny!\n\nRarity: Legendary",
    "icon_url": "https://i.ibb.co/3YJjSr2/pug-metal4.png",
    "tradable": true,
    "marketable": true,
    "commodity": false,
    "quality": "common"
  },
  {
    "appid": "3067050",
    "itemdefid": "40",
    "Timestamp": "2024-07-24T15:22:54Z",
    "modified": "20240724T152254Z",
    "date_created": "20240705T221820Z",
    "type": "item",
    "display_type": "",
    "name": "P ... ...",
    "quantity": 1,
    "description": "This Pug is a P\n\nRarity: Uncommon",
    "icon_url": "https://i.ibb.co/Vtx75Wg/pug-letter1.png",
    "tradable": true,
    "marketable": true,
    "commodity": false,
    "quality": "common"
  },
  {
    "appid": "3067050",
    "itemdefid": "41",
    "Timestamp": "2024-08-02T22:12:11Z",
    "modified": "20240802T221211Z",
    "date_created": "20240705T221820Z",
    "type": "item",
    "display_type": "",
    "name": "U ... ...",
    "quantity": 1,
    "description": "This Pug is a U\n\nRarity: Uncommon",
    "icon_url": "https://i.ibb.co/BCyx51K/pug-letter2.png",
    "tradable": true,
    "marketable": true,
    "commodity": false,
    "quality": "common"
  },
  {
    "appid": "3067050",
    "itemdefid": "42",
    "Timestamp": "2024-08-02T22:12:00Z",
    "modified": "20240802T221200Z",
    "date_created": "20240705T221820Z",
    "type": "item",
    "display_type": "",
    "name": "G ... ...",
    "quantity": 1,
    "description": "This Pug is a G\n\nRarity: Uncommon",
    "icon_url": "https://i.ibb.co/QQMwDwf/pug-letter3.png",
    "tradable": true,
    "marketable": true,
    "commodity": false,
    "quality": "common"
  },
  {
    "appid": "3067050",
    "itemdefid": "50",
    "Timestamp": "2024-07-24T15:22:28Z",
    "modified": "20240724T152228Z",
    "date_created": "20240705T221820Z",
    "type": "item",
    "display_type": "",
    "name": "Close Pug",
    "quantity": 1,
    "description": "He got too close!\n\nRarity: Uncommon",
    "icon_url": "https://i.ibb.co/VYLPdyP/pug-distance1.png",
    "tradable": true,
    "marketable": true,
    "commodity": false,
    "quality": "common"
  },
  {
    "appid": "3067050",
    "itemdefid": "51",
    "Timestamp": "2024-07-24T15:22:36Z",
    "modified": "20240724T152236Z",
    "date_created": "20240705T221820Z",
    "type": "item",
    "display_type": "",
    "name": "Far Pug",
    "quantity": 1,
    "description": "He got too far!\n\nRarity: Uncommon",
    "icon_url": "https://i.ibb.co/867R366/pug-distance2.png",
    "tradable": true,
    "marketable": true,
    "commodity": false,
    "quality": "common"
  },
  {
    "appid": "3067050",
    "itemdefid": "60",
    "Timestamp": "2024-08-17T01:35:12Z",
    "modified": "20240817T013512Z",
    "date_created": "20240705T221820Z",
    "type": "item",
    "display_type": "",
    "name": "Dummy Pug",
    "quantity": 1,
    "description": "Used during tests and experiments, its so well done it looks real\n\nRarity: Limited\n\nNo longer Drops",
    "icon_url": "https://i.ibb.co/72gz6ns/pug-dummy.png",
    "tradable": true,
    "marketable": true,
    "commodity": false,
    "quality": "common"
  },
  {
    "appid": "3067050",
    "itemdefid": "70",
    "Timestamp": "2024-07-05T22:24:39Z",
    "modified": "20240705T222439Z",
    "date_created": "20240705T221820Z",
    "type": "item",
    "display_type": "",
    "name": "free",
    "quantity": 1,
    "description": "",
    "tradable": true,
    "marketable": true,
    "commodity": false,
    "quality": "common"
  },
  {
    "appid": "3067050",
    "itemdefid": "71",
    "Timestamp": "2024-07-24T15:24:02Z",
    "modified": "20240724T152402Z",
    "date_created": "20240705T221820Z",
    "type": "item",
    "display_type": "",
    "name": "Pug Lee",
    "quantity": 1,
    "description": "He's a Martial Arts fan\n\nRarity: Rare",
    "icon_url": "https://i.ibb.co/GsqLGzm/pug-lee.png",
    "tradable": true,
    "marketable": true,
    "commodity": false,
    "quality": "common"
  },
  {
    "appid": "3067050",
    "itemdefid": "72",
    "Timestamp": "2024-07-24T15:20:28Z",
    "modified": "20240724T152028Z",
    "date_created": "20240705T221820Z",
    "type": "item",
    "display_type": "",
    "name": "Alerted Pug",
    "quantity": 1,
    "description": "Don't even try to sneak up to him.\n\nRarity: Common",
    "icon_url": "https://i.ibb.co/HdLvHck/pug-earup.png",
    "tradable": true,
    "marketable": true,
    "commodity": false,
    "quality": "common"
  },
  {
    "appid": "3067050",
    "itemdefid": "73",
    "Timestamp": "2024-07-24T15:23:04Z",
    "modified": "20240724T152304Z",
    "date_created": "20240705T221820Z",
    "type": "item",
    "display_type": "",
    "name": "Pugtchoo",
    "quantity": 1,
    "description": "Atchoo!!. Bless you!\n\nRarity: Uncommon",
    "icon_url": "https://i.ibb.co/Z18btwj/pug-sick.png",
    "tradable": true,
    "marketable": true,
    "commodity": false,
    "quality": "common"
  },
  {
    "appid": "3067050",
    "itemdefid": "74",
    "Timestamp": "2024-07-24T15:24:37Z",
    "modified": "20240724T152437Z",
    "date_created": "20240705T221820Z",
    "type": "item",
    "display_type": "",
    "name": "TransPUGarent",
    "quantity": 1,
    "description": "He cast shadows tho\n\nRarity: Rare",
    "icon_url": "https://i.ibb.co/swZSjRR/pug-transparente.png",
    "tradable": true,
    "marketable": true,
    "commodity": false,
    "quality": "common"
  },
  {
    "appid": "3067050",
    "itemdefid": "80",
    "Timestamp": "2024-07-24T15:24:28Z",
    "modified": "20240724T152428Z",
    "date_created": "20240705T221820Z",
    "type": "item",
    "display_type": "",
    "name": "Puget Spiner",
    "quantity": 1,
    "description": "He Spins\n\nRarity: Rare",
    "icon_url": "https://i.ibb.co/nPmhMRk/pug-circles.gif",
    "tradable": true,
    "marketable": true,
    "commodity": false,
    "quality": "common"
  },
  {
    "appid": "3067050",
    "itemdefid": "81",
    "Timestamp": "2024-07-24T15:25:31Z",
    "modified": "20240724T152531Z",
    "date_created": "20240705T221820Z",
    "type": "item",
    "display_type": "",
    "name": "Vibing Pug",
    "quantity": 1,
    "description": "Maybe he's listening to Pugsy - 'Oppug Pugnam style'\n\nRarity: Legendary",
    "icon_url": "https://i.ibb.co/H4fcYKb/pug-pugmusic.gif",
    "tradable": true,
    "marketable": true,
    "commodity": false,
    "quality": "common"
  },
  {
    "appid": "3067050",
    "itemdefid": "82",
    "Timestamp": "2024-07-24T15:25:20Z",
    "modified": "20240724T152520Z",
    "date_created": "20240705T221821Z",
    "type": "item",
    "display_type": "",
    "name": "Astro Pug",
    "quantity": 1,
    "description": "To infinity, and beyond!\n\nRarity: Legendary",
    "icon_url": "https://i.ibb.co/wM2b3gT/pug-pugonaut.gif",
    "tradable": true,
    "marketable": true,
    "commodity": false,
    "quality": "common"
  },
  {
    "appid": "3067050",
    "itemdefid": "83",
    "Timestamp": "2024-07-24T15:25:04Z",
    "modified": "20240724T152504Z",
    "date_created": "20240705T221821Z",
    "type": "item",
    "display_type": "",
    "name": "CODE RGB: Recasting Gene Behavior",
    "quantity": 1,
    "description": "You better fix him this time.\n\nRarity: Legendary",
    "icon_url": "https://i.ibb.co/F3LHGQF/pug-rgb.gif",
    "tradable": true,
    "marketable": true,
    "commodity": false,
    "quality": "common"
  },
  {
    "appid": "3067050",
    "itemdefid": "84",
    "Timestamp": "2024-07-24T15:24:43Z",
    "modified": "20240724T152443Z",
    "date_created": "20240705T221821Z",
    "type": "item",
    "display_type": "",
    "name": "The Puglight Zone",
    "quantity": 1,
    "description": "What a mystery\n\nRarity: Rare",
    "icon_url": "https://i.ibb.co/M63v4LY/pug-puglightzone.gif",
    "tradable": true,
    "marketable": true,
    "commodity": false,
    "quality": "common"
  },
  {
    "appid": "3067050",
    "itemdefid": "85",
    "Timestamp": "2024-08-17T14:40:12Z",
    "modified": "20240817T144012Z",
    "date_created": "20240705T221821Z",
    "type": "item",
    "display_type": "",
    "name": "SpiderPug",
    "quantity": 1,
    "description": "I swear I have seen this movie about a dog being bitten by a spider.\n\nRarity: Rare\n\nNo longer drops",
    "icon_url": "https://i.ibb.co/7nZcWt8/pug-slidedown.gif",
    "tradable": true,
    "marketable": true,
    "commodity": false,
    "quality": "common"
  },
  {
    "appid": "3067050",
    "itemdefid": "90",
    "Timestamp": "2024-08-17T01:34:05Z",
    "modified": "20240817T013405Z",
    "date_created": "20240817T012400Z",
    "type": "item",
    "display_type": "",
    "name": "Pugdates",
    "quantity": 1,
    "description": "He's always around testing and working for the FIX.",
    "icon_url": "https://i.ibb.co/qDr5CG2/upugdates.png",
    "tradable": true,
    "marketable": true,
    "commodity": false,
    "quality": "common"
  },
  {
    "appid": "3067050",
    "itemdefid": "91",
    "Timestamp": "2024-08-17T01:40:34Z",
    "modified": "20240817T014034Z",
    "date_created": "20240817T012400Z",
    "type": "item",
    "display_type": "",
    "name": "Tour Pug",
    "quantity": 1,
    "description": "He just loves to take a walk.\n\nIdeia: Asanaparada",
    "icon_url": "https://i.ibb.co/BzXc95x/Pug-Tour.png",
    "tradable": true,
    "marketable": true,
    "commodity": false,
    "quality": "common"
  },
  {
    "appid": "3067050",
    "itemdefid": "98",
    "Timestamp": "2024-09-01T23:17:33Z",
    "modified": "20240901T231733Z",
    "date_created": "20240817T012401Z",
    "type": "item",
    "display_type": "",
    "name": "Pug The Artist",
    "quantity": 1,
    "description": "Such open minded Pug he is!\n\nNo longer Drops",
    "icon_url": "https://i.ibb.co/gjBGJf1/pug-artist.png",
    "tradable": true,
    "marketable": true,
    "commodity": false,
    "quality": "common"
  },
  {
    "appid": "3067050",
    "itemdefid": "99",
    "Timestamp": "2024-08-17T01:26:05Z",
    "modified": "20240817T012605Z",
    "date_created": "20240817T012401Z",
    "type": "item",
    "display_type": "",
    "name": "Pug The Dev",
    "quantity": 1,
    "description": "He is trully a home dog.",
    "icon_url": "https://i.ibb.co/sQGtgK8/Pug-Dev.png",
    "tradable": true,
    "marketable": true,
    "commodity": false,
    "quality": "common"
  },
  {
    "appid": "3067050",
    "itemdefid": "300",
    "Timestamp": "2024-08-17T01:35:23Z",
    "modified": "20240817T013523Z",
    "date_created": "20240705T211351Z",
    "type": "generator",
    "display_type": "",
    "name": "Common generator",
    "quantity": 0,
    "description": "",
    "background_color": "3C352E",
    "name_color": "7D6D00",
    "tradable": false,
    "marketable": false,
    "commodity": false
  },
  {
    "appid": "3067050",
    "itemdefid": "400",
    "Timestamp": "2024-08-17T11:08:49Z",
    "modified": "20240817T110849Z",
    "date_created": "20240705T211351Z",
    "type": "generator",
    "display_type": "",
    "name": "Normal generator",
    "quantity": 0,
    "description": "",
    "background_color": "3C352E",
    "name_color": "7D6D00",
    "tradable": false,
    "marketable": false,
    "commodity": false
  },
  {
    "appid": "3067050",
    "itemdefid": "500",
    "Timestamp": "2024-09-08T17:52:37Z",
    "modified": "20240908T175237Z",
    "date_created": "20240705T211351Z",
    "type": "generator",
    "display_type": "",
    "name": "Special generator",
    "quantity": 0,
    "description": "",
    "background_color": "3C352E",
    "name_color": "7D6D00",
    "tradable": false,
    "marketable": false,
    "commodity": false
  },
  {
    "appid": "3067050",
    "itemdefid": "600",
    "Timestamp": "2025-06-08T19:53:41Z",
    "modified": "20250608T195341Z",
    "date_created": "20240705T222604Z",
    "type": "generator",
    "display_type": "",
    "name": "Rare generator",
    "quantity": 0,
    "description": "",
    "background_color": "3C352E",
    "name_color": "7D6D00",
    "tradable": false,
    "marketable": false,
    "commodity": false
  },
  {
    "appid": "3067050",
    "itemdefid": "1001",
    "Timestamp": "2024-07-05T22:19:11Z",
    "modified": "20240705T221911Z",
    "date_created": "20240621T183540Z",
    "type": "item",
    "display_type": "",
    "name": "Testtest",
    "quantity": 1,
    "description": ".",
    "tradable": false,
    "marketable": false,
    "commodity": false,
    "quality": "common"
  }
]